ethtx/__init__.py
ethtx/ethtx.py
ethtx/exceptions.py
ethtx/decoders/__init__.py
ethtx/decoders/decoder_service.py
ethtx/decoders/abi/__init__.py
ethtx/decoders/abi/abc.py
ethtx/decoders/abi/balances.py
ethtx/decoders/abi/calls.py
ethtx/decoders/abi/decoder.py
ethtx/decoders/abi/events.py
ethtx/decoders/abi/transfers.py
ethtx/decoders/abi/helpers/__init__.py
ethtx/decoders/abi/helpers/utils.py
ethtx/decoders/decoders/__init__.py
ethtx/decoders/decoders/errors.py
ethtx/decoders/decoders/parameters.py
ethtx/decoders/decoders/semantics.py
ethtx/decoders/semantic/__init__.py
ethtx/decoders/semantic/abc.py
ethtx/decoders/semantic/balances.py
ethtx/decoders/semantic/calls.py
ethtx/decoders/semantic/decoder.py
ethtx/decoders/semantic/events.py
ethtx/decoders/semantic/metadata.py
ethtx/decoders/semantic/transfers.py
ethtx/decoders/semantic/helpers/__init__.py
ethtx/decoders/semantic/helpers/utils.py
ethtx/models/__init__.py
ethtx/models/_types.py
ethtx/models/base_model.py
ethtx/models/decoded_model.py
ethtx/models/objects_model.py
ethtx/models/semantics_model.py
ethtx/models/w3_model.py
ethtx/providers/__init__.py
ethtx/providers/ens_provider.py
ethtx/providers/signature_provider.py
ethtx/providers/web3_provider.py
ethtx/providers/etherscan/__init__.py
ethtx/providers/etherscan/client.py
ethtx/providers/etherscan/contracts.py
ethtx/providers/etherscan/etherscan_provider.py
ethtx/providers/node/__init__.py
ethtx/providers/node/connection_base.py
ethtx/providers/node/pool.py
ethtx/providers/semantic_providers/__init__.py
ethtx/providers/semantic_providers/base.py
ethtx/providers/semantic_providers/const.py
ethtx/providers/semantic_providers/database.py
ethtx/providers/semantic_providers/repository.py
ethtx/providers/static/tracer.js
ethtx/semantics/__init__.py
ethtx/semantics/base.py
ethtx/semantics/protocols_router.py
ethtx/semantics/router.py
ethtx/semantics/protocols/__init__.py
ethtx/semantics/protocols/anonymous.py
ethtx/semantics/protocols/maker/__init__.py
EthTx-0.3.22.dist-info/LICENSE
EthTx-0.3.22.dist-info/METADATA
EthTx-0.3.22.dist-info/WHEEL
EthTx-0.3.22.dist-info/top_level.txt
EthTx-0.3.22.dist-info/RECORD
