Metadata-Version: 2.1
Name: EthTx
Version: 0.3.22
Summary: EthTx transaction decoder.
Home-page: https://github.com/EthTx/ethtx
Author: Karol Chojnowski, Tomasz Mierzwa, Piotr Rudnik
Author-email: karol@tfi.team, tomek@tfi.team, piotr.rudnik@tfi.team
License: Apache-2.0 License
Classifier: Operating System :: POSIX :: Linux
Classifier: Programming Language :: Python :: 3.8
Classifier: Programming Language :: Python :: 3.9
Requires-Python: >=3.7.0
License-File: LICENSE
Requires-Dist: toml
Requires-Dist: pymongo (<4.0,>=3.10.0)
Requires-Dist: dnspython (>=2.0.0)
Requires-Dist: mongoengine (<0.27.0)
Requires-Dist: mongomock
Requires-Dist: web3 (<7.0.0,>=6.0.0)
Requires-Dist: pydantic (>=1.8.0)
Requires-Dist: python-dotenv
Requires-Dist: requests
